CONTRIBUTING.rst
HISTORY.rst
LICENSE
MANIFEST.in
README.rst
setup.cfg
setup.py
meta_tagger/__init__.py
meta_tagger/admin.py
meta_tagger/cms_sitemap.py
meta_tagger/cms_toolbars.py
meta_tagger/conf.py
meta_tagger/helpers.py
meta_tagger/models.py
meta_tagger/views.py
meta_tagger.egg-info/PKG-INFO
meta_tagger.egg-info/SOURCES.txt
meta_tagger.egg-info/dependency_links.txt
meta_tagger.egg-info/not-zip-safe
meta_tagger.egg-info/requires.txt
meta_tagger.egg-info/top_level.txt
meta_tagger/migrations/0001_initial.py
meta_tagger/migrations/0002_auto_20160527_1656.py
meta_tagger/migrations/0003_auto_20181108_0934.py
meta_tagger/migrations/0004_auto_20190702_1510.py
meta_tagger/migrations/__init__.py
meta_tagger/templates/meta_tagger/meta_tags.html
meta_tagger/templates/meta_tagger/robots.txt
meta_tagger/templatetags/__init__.py
meta_tagger/templatetags/meta_tagger_tags.py
tests/test_models.py
tests/test_views.py