Metadata-Version: 2.1
Name: meta-tagger
Version: 0.1.14
Summary: Your project description goes here
Home-page: https://github.com/dreipol/meta-tagger
Author: dreipol GmbH
Author-email: dev@dreipol.ch
License: BSD
Keywords: meta-tagger
Classifier: Development Status :: 3 - Alpha
Classifier: Framework :: Django
Classifier: Framework :: Django :: 1.8
Classifier: Framework :: Django :: 1.9
Classifier: Intended Audience :: Developers
Classifier: License :: OSI Approved :: BSD License
Classifier: Natural Language :: English
Classifier: Programming Language :: Python :: 3
Classifier: Programming Language :: Python :: 3.3
Classifier: Programming Language :: Python :: 3.4
Classifier: Programming Language :: Python :: 3.5
Classifier: Programming Language :: Python :: 3.6
Classifier: Programming Language :: Python :: 3.7
Classifier: Programming Language :: Python :: 3.8
Classifier: Programming Language :: Python :: 3.9
Classifier: Programming Language :: Python :: 3.10
Classifier: Programming Language :: Python :: 3.11
License-File: LICENSE
Requires-Dist: django>=1.8
Requires-Dist: django-cms>=3.0
Requires-Dist: django-filer>=1.1.0
Requires-Dist: django-appconf>=1.0.1
Requires-Dist: easy-thumbnails>=2.2
